./.gitignore
./.python-version
./LICENSE
./PKG-INFO
./README.md
./llm_api_server.py
./pyproject.toml
./pytest.ini
./ruff.toml
./tests/test_integration.py
llm_api_server-0.1.0.dist-info/METADATA
llm_api_server-0.1.0.dist-info/WHEEL
llm_api_server-0.1.0.dist-info/entry_points.txt
llm_api_server-0.1.0.dist-info/licenses/LICENSE
llm_api_server-0.1.0.dist-info/RECORD
