Metadata-Version: 2.4
Name: llm-api-server
Version: 0.1.0
Summary: LLM plugin to expose a FastAPI server with compatible APIs for popular LLM clients
Project-URL: Homepage, https://github.com/danielcorin/llm-api
Project-URL: Documentation, https://github.com/danielcorin/llm-api#readme
Project-URL: Repository, https://github.com/danielcorin/llm-api
Project-URL: Issues, https://github.com/danielcorin/llm-api/issues
Author-email: Daniel Corin <dan@wvlen.llc>
License: MIT
License-File: LICENSE
Keywords: api,fastapi,llm,openai,server
Classifier: Development Status :: 3 - Alpha
Classifier: Framework :: FastAPI
Classifier: Intended Audience :: Developers
Classifier: License :: OSI Approved :: MIT License
Classifier: Programming Language :: Python :: 3
Classifier: Programming Language :: Python :: 3.9
Classifier: Programming Language :: Python :: 3.10
Classifier: Programming Language :: Python :: 3.11
Classifier: Programming Language :: Python :: 3.12
Classifier: Topic :: Software Development :: Libraries :: Python Modules
Requires-Python: >=3.9
Requires-Dist: fastapi>=0.104.0
Requires-Dist: httpx>=0.25.0
Requires-Dist: llm>=0.15
Requires-Dist: pydantic>=2.0
Requires-Dist: uvicorn>=0.24.0
